nor1029_controller/__init__.py
nor1029_controller/py.typed
nor1029_controller-0.5.0.dist-info/METADATA
nor1029_controller-0.5.0.dist-info/WHEEL
nor1029_controller-0.5.0.dist-info/licenses/license
nor1029_controller-0.5.0.dist-info/RECORD
