Metadata-Version: 2.4
Name: nor1029-controller
Version: 0.5.0
Summary: Programmatically control Norsonic Nor1029
Project-URL: repository, https://github.com/Richienb/nor1029-controller.git
Author-email: Richie Bendall <richiebendall@gmail.com>
License-Expression: MIT
License-File: license
Requires-Python: >=3.11
Requires-Dist: pyserial>=3.5
